eventhub/__init__.py
eventhub-0.0.0.dist-info/METADATA
eventhub-0.0.0.dist-info/WHEEL
eventhub-0.0.0.dist-info/RECORD
