Metadata-Version: 2.1
Name: eventhub
Version: 0.0.0
Summary: a lightweight event library
Author: Dan Sikes
Author-email: dan@apagea.com
Requires-Python: >=3.9,<4.0
Classifier: Programming Language :: Python :: 3
Classifier: Programming Language :: Python :: 3.9
Classifier: Programming Language :: Python :: 3.10
Classifier: Programming Language :: Python :: 3.11
Classifier: Programming Language :: Python :: 3.12
